{
  "project_info": {
    "project_number": "663594485566",
    "project_id": "mykirana-b00e1",
    "storage_bucket": "mykirana-b00e1.firebasestorage.app"
  },
  "client": [
    {
      "client_info": {
        "mobilesdk_app_id": "1:663594485566:android:7f02a2d1698c9cf5dc4e6f",
        "android_client_info": {
          "package_name": "com.vijaybore.mykirana"
        }
      },
      "oauth_client": [],
      "api_key": [
        {
          "current_key": "AIzaSyAQtSE9Nc0vmDl8KzUG1ldr9lfL7DXWybg"
        }
      ],
      "services": {
        "appinvite_service": {
          "other_platform_oauth_client": []
        }
      }
    }
  ],
  "configuration_version": "1"
}